{
    "particleeffect": {
        "direction": {
            "max": "-1.0 0.0 1.0",
            "min": "0.0 1.0 -1.0",
            "value": "Direction"
        },
        "emissionrate": {
            "max": "6.0",
            "min": "8.0"
        },
        "emitterScaleCurve": [],
        "emitterscale": [],
        "emittersize": {
            "value": "2.0 3.0 1.0"
        },
        "emittertype": {
            "value": "Box"
        },
        "enabletexture": {
            "enable": true
        },
        "numparticles": {
            "value": "8"
        },
        "particlesize": {
            "max": "0.25 0.25",
            "min": "0.35 0.35"
        },
        "pointFiltering": true,
        "relative": {
            "enable": "true"
        },
        "rotationRange": {
            "max": "0.0 -30.0 -10.0",
            "min": "0.0 30.0 10.0"
        },
        "texture": {
            "ani": {
                "fps": "20",
                "name": "textures/sfxs/2025s2/cs_s4diaoling_horse_huolz",
                "shuffle": false
            },
            "name": "textures/sfxs/2025s2/cs_s4diaoling_horse_huolz"
        },
        "thickness": {
            "value": "0.0"
        },
        "timetolive": {
            "max": "0.8",
            "min": "0.5"
        },
        "velocity": {
            "max": "0.0",
            "min": "0.0"
        }
    }
}