{
    "particleeffect": {
        "activetime": {
            "value": "0.2"
        },
        "colorfade": [
            {
                "color": "0.9686 0.0000 1.0000 1.0000",
                "time": "0.0%"
            },
            {
                "color": "0.9686 0.0000 1.0000 0.9375",
                "time": "20.0%"
            },
            {
                "color": "1.0000 0.0000 1.0000 0.6696",
                "time": "39.7%"
            },
            {
                "color": "1.0000 0.0000 1.0000 0.1339",
                "time": "55.5%"
            },
            {
                "color": "1.0000 1.0000 1.0000 0.0000",
                "time": "76.3%"
            },
            {
                "color": "1.0000 1.0000 1.0000 0.0000",
                "time": "100.0%"
            }
        ],
        "direction": {
            "max": "0.0 0.0 0.0",
            "min": "0.0 0.0 0.0",
            "value": "Direction"
        },
        "emissionrate": {
            "max": "20.0",
            "min": "20.0"
        },
        "enabletexture": {
            "enable": true
        },
        "numparticles": {
            "value": "1"
        },
        "particlesize": {
            "max": "0.08 0.08",
            "min": "0.08 0.08"
        },
        "pointFiltering": true,
        "relative": {
            "enable": "true"
        },
        "sizedelta": [
            {
                "scale": "0.09 0.09",
                "time": "0.0%"
            },
            {
                "scale": "1.08 1.08",
                "time": "10.0%"
            },
            {
                "scale": "1.07 1.07",
                "time": "28.0%"
            },
            {
                "scale": "1.12 1.12",
                "time": "45.0%"
            },
            {
                "scale": "1.08 1.08",
                "time": "68.7%"
            },
            {
                "scale": "1.35 1.35",
                "time": "83.8%"
            },
            {
                "scale": "1.41 1.41",
                "time": "100.0%"
            }
        ],
        "texture": {
            "ani": {
                "fps": "6",
                "name": "textures/sfxs/emote/cs_game_skinb_emotes_smoke",
                "shuffle": false
            },
            "name": "textures/sfxs/emote/cs_game_skinb_emotes_smoke"
        },
        "timetolive": {
            "max": "1.5",
            "min": "1.2"
        },
        "velocity": {
            "max": "0.0",
            "min": "0.0"
        }
    }
}