{
    "frames": [
        {
            "filename": "1_000.png",
            "frame": {
                "x": 0,
                "y": 0,
                "w": 256,
                "h": 512
            },
            "rotated": false,
            "trimmed": false,
            "spriteSourceSize": {
                "x": 0,
                "y": 0,
                "w": 256,
                "h": 512
            },
            "sourceSize": {
                "w": 256,
                "h": 512
            }
        },
        {
            "filename": "1_001.png",
            "frame": {
                "x": 256,
                "y": 0,
                "w": 256,
                "h": 512
            },
            "rotated": false,
            "trimmed": false,
            "spriteSourceSize": {
                "x": 0,
                "y": 0,
                "w": 256,
                "h": 512
            },
            "sourceSize": {
                "w": 256,
                "h": 512
            }
        }
    ],
    "meta": {
        "app": "https://www.codeandweb.com/texturepacker",
        "version": "1.0",
        "image": "sh_s3guofeng_skinA_xulilz02.png",
        "format": "RGBA8888",
        "size": {
            "w": 512,
            "h": 512
        },
        "scale": "1",
        "smartupdate": "$TexturePacker:SmartUpdate:175e74b52fcf15d0edfd13663d2b6709:7602282dd6893ede6d98613fed338fd3:ead59085afc524fcaa07212adb0a5121$"
    }
}