{
    "frames": [
        {
            "filename": "ss_s6FireDragon_fp_kzd.png",
            "frame": {
                "x": 0,
                "y": 0,
                "w": 32,
                "h": 32
            },
            "rotated": false,
            "trimmed": false,
            "spriteSourceSize": {
                "x": 0,
                "y": 0,
                "w": 32,
                "h": 32
            },
            "sourceSize": {
                "w": 32,
                "h": 32
            }
        },
        {
            "filename": "ss_s6FireDragon_fp_kzx.png",
            "frame": {
                "x": 32,
                "y": 0,
                "w": 32,
                "h": 32
            },
            "rotated": false,
            "trimmed": false,
            "spriteSourceSize": {
                "x": 0,
                "y": 0,
                "w": 32,
                "h": 32
            },
            "sourceSize": {
                "w": 32,
                "h": 32
            }
        }
    ],
    "meta": {
        "app": "https://www.codeandweb.com/texturepacker",
        "version": "1.0",
        "image": "ss_s6FireDragon_fp_lzh.png",
        "format": "RGBA8888",
        "size": {
            "w": 64,
            "h": 32
        },
        "scale": "1",
        "smartupdate": "$TexturePacker:SmartUpdate:dcd3ccf089b381c5ab3d09c36c866294:11b32184f3abd3fdcdfdbe01a0f38bf8:b66d48312fb878cd9ce53520ab507418$"
    }
}