{
    "frames": [
        {
            "filename": "paopao_01.png",
            "frame": {
                "x": 0,
                "y": 0,
                "w": 128,
                "h": 128
            },
            "rotated": false,
            "trimmed": false,
            "spriteSourceSize": {
                "x": 0,
                "y": 0,
                "w": 128,
                "h": 128
            },
            "sourceSize": {
                "w": 128,
                "h": 128
            }
        },
        {
            "filename": "paopao_02.png",
            "frame": {
                "x": 128,
                "y": 0,
                "w": 128,
                "h": 128
            },
            "rotated": false,
            "trimmed": false,
            "spriteSourceSize": {
                "x": 0,
                "y": 0,
                "w": 128,
                "h": 128
            },
            "sourceSize": {
                "w": 128,
                "h": 128
            }
        },
        {
            "filename": "paopao_03.png",
            "frame": {
                "x": 256,
                "y": 0,
                "w": 128,
                "h": 128
            },
            "rotated": false,
            "trimmed": false,
            "spriteSourceSize": {
                "x": 0,
                "y": 0,
                "w": 128,
                "h": 128
            },
            "sourceSize": {
                "w": 128,
                "h": 128
            }
        },
        {
            "filename": "paopao_04.png",
            "frame": {
                "x": 384,
                "y": 0,
                "w": 128,
                "h": 128
            },
            "rotated": false,
            "trimmed": false,
            "spriteSourceSize": {
                "x": 0,
                "y": 0,
                "w": 128,
                "h": 128
            },
            "sourceSize": {
                "w": 128,
                "h": 128
            }
        },
        {
            "filename": "paopao_05.png",
            "frame": {
                "x": 0,
                "y": 128,
                "w": 128,
                "h": 128
            },
            "rotated": false,
            "trimmed": false,
            "spriteSourceSize": {
                "x": 0,
                "y": 0,
                "w": 128,
                "h": 128
            },
            "sourceSize": {
                "w": 128,
                "h": 128
            }
        },
        {
            "filename": "paopao_06.png",
            "frame": {
                "x": 128,
                "y": 128,
                "w": 128,
                "h": 128
            },
            "rotated": false,
            "trimmed": false,
            "spriteSourceSize": {
                "x": 0,
                "y": 0,
                "w": 128,
                "h": 128
            },
            "sourceSize": {
                "w": 128,
                "h": 128
            }
        },
        {
            "filename": "paopao_07.png",
            "frame": {
                "x": 256,
                "y": 128,
                "w": 128,
                "h": 128
            },
            "rotated": false,
            "trimmed": false,
            "spriteSourceSize": {
                "x": 0,
                "y": 0,
                "w": 128,
                "h": 128
            },
            "sourceSize": {
                "w": 128,
                "h": 128
            }
        },
        {
            "filename": "paopao_08.png",
            "frame": {
                "x": 384,
                "y": 128,
                "w": 128,
                "h": 128
            },
            "rotated": false,
            "trimmed": false,
            "spriteSourceSize": {
                "x": 0,
                "y": 0,
                "w": 128,
                "h": 128
            },
            "sourceSize": {
                "w": 128,
                "h": 128
            }
        }
    ],
    "meta": {
        "app": "http://www.texturepacker.com",
        "version": "1.0",
        "image": "ss_elem_horse_pao02.png",
        "format": "RGBA8888",
        "size": {
            "w": 512,
            "h": 256
        },
        "scale": "1",
        "smartupdate": "$TexturePacker:SmartUpdate:15b1ceb26007cce51a091b7c5cfe1236$"
    }
}