{
    "position": {
        "0.0": [
            7.30856228,
            1.8538065,
            0.0
        ],
        "0.033": [
            4.86523056,
            1.97177482,
            0.0
        ],
        "0.067": [
            4.86524343,
            1.97177505,
            2.4e-07
        ],
        "0.1": [
            4.86527443,
            1.97177482,
            0.0
        ],
        "0.133": [
            4.86534309,
            1.97177482,
            0.0
        ],
        "0.167": [
            4.86544991,
            1.97177529,
            0.0
        ],
        "0.2": [
            4.86561251,
            1.97177529,
            2.4e-07
        ],
        "0.233": [
            4.86583757,
            1.97177482,
            -2.4e-07
        ],
        "0.267": [
            4.86613083,
            1.97177482,
            0.0
        ],
        "0.3": [
            4.86651897,
            1.97177458,
            -2.4e-07
        ],
        "0.333": [
            4.8669939,
            1.97177458,
            -2.4e-07
        ],
        "0.367": [
            4.86757469,
            1.97177482,
            0.0
        ],
        "0.4": [
            4.86827517,
            1.97177482,
            0.0
        ],
        "0.433": [
            4.86910582,
            1.97177529,
            0.0
        ],
        "0.467": [
            4.87006855,
            1.97177482,
            0.0
        ],
        "0.5": [
            4.87118149,
            1.97177458,
            -2.4e-07
        ],
        "0.533": [
            4.87244987,
            1.97177458,
            -2.4e-07
        ],
        "0.567": [
            4.87389374,
            1.97177458,
            -2.4e-07
        ],
        "0.6": [
            4.87551212,
            1.97177529,
            0.0
        ],
        "0.633": [
            4.87732506,
            1.97177517,
            0.0
        ],
        "0.667": [
            4.87933731,
            1.97177517,
            0.0
        ],
        "0.7": [
            4.88156271,
            1.97177505,
            -2.4e-07
        ],
        "0.733": [
            4.88400555,
            1.97177482,
            0.0
        ],
        "0.767": [
            4.88668728,
            1.97177529,
            2.4e-07
        ],
        "0.8": [
            4.88960648,
            1.97177529,
            0.0
        ],
        "0.833": [
            4.89278126,
            1.97177505,
            -2.4e-07
        ],
        "0.867": [
            4.89622498,
            1.97177517,
            0.0
        ],
        "0.9": [
            4.89993763,
            1.97177482,
            0.0
        ],
        "0.933": [
            4.90393734,
            1.97177458,
            -2.4e-07
        ],
        "0.967": [
            4.90823698,
            1.97177529,
            0.0
        ],
        "1.0": [
            4.9128437,
            1.97177517,
            0.0
        ],
        "1.033": [
            4.9177618,
            1.97177482,
            0.0
        ],
        "1.067": [
            4.92301226,
            1.97177505,
            2.4e-07
        ],
        "1.1": [
            4.92859983,
            1.97177517,
            0.0
        ],
        "1.133": [
            4.93453693,
            1.97177482,
            0.0
        ],
        "1.167": [
            4.94083738,
            1.97177482,
            -2.4e-07
        ],
        "1.2": [
            4.94750023,
            1.97177529,
            0.0
        ],
        "1.233": [
            4.95454979,
            1.97177529,
            2.4e-07
        ],
        "1.267": [
            4.96198702,
            1.97177505,
            2.4e-07
        ],
        "1.3": [
            4.96983099,
            1.97177505,
            2.4e-07
        ],
        "1.333": [
            4.97808743,
            1.97177458,
            -2.4e-07
        ],
        "1.367": [
            4.98676252,
            1.97177517,
            0.0
        ],
        "1.4": [
            4.9958744,
            1.97177482,
            0.0
        ],
        "1.433": [
            5.00543118,
            1.97177517,
            0.0
        ],
        "1.467": [
            5.01883698,
            1.97194374,
            0.0
        ],
        "1.5": [
            5.0392313,
            1.97243702,
            0.0
        ],
        "1.533": [
            5.06619358,
            1.9732374,
            0.0
        ],
        "1.567": [
            5.09930611,
            1.9743247,
            -2.4e-07
        ],
        "1.6": [
            5.13816261,
            1.97568095,
            0.0
        ],
        "1.633": [
            5.18234348,
            1.97729373,
            0.0
        ],
        "1.667": [
            5.23143721,
            1.97913766,
            2.4e-07
        ],
        "1.7": [
            5.28503132,
            1.98119354,
            -2.4e-07
        ],
        "1.733": [
            5.34271193,
            1.98344982,
            0.0
        ],
        "1.767": [
            5.40406227,
            1.98588705,
            -2.4e-07
        ],
        "1.8": [
            5.46866894,
            1.98848701,
            -2.4e-07
        ],
        "1.833": [
            5.53612518,
            1.99122477,
            -4.8e-07
        ],
        "1.867": [
            5.60600567,
            1.99409378,
            0.0
        ],
        "1.9": [
            5.67791271,
            1.99706888,
            2.4e-07
        ],
        "1.933": [
            5.75141191,
            2.00013137,
            0.0
        ],
        "1.967": [
            5.82611179,
            2.00326228,
            -2.4e-07
        ],
        "2.0": [
            5.90158081,
            2.00645041,
            0.0
        ],
        "2.033": [
            5.97741222,
            2.00967455,
            -2.4e-07
        ],
        "2.067": [
            6.05319357,
            2.01291227,
            4.8e-07
        ],
        "2.1": [
            6.12850571,
            2.01615,
            4.8e-07
        ],
        "2.133": [
            6.2029438,
            2.01936245,
            4.8e-07
        ],
        "2.167": [
            6.27606201,
            2.02254343,
            4.8e-07
        ],
        "2.2": [
            6.34749985,
            2.02566862,
            0.0
        ],
        "2.233": [
            6.41681242,
            2.02871275,
            0.0
        ],
        "2.267": [
            6.48362494,
            2.03167462,
            0.0
        ],
        "2.3": [
            6.54743671,
            2.03451943,
            4.8e-07
        ],
        "2.333": [
            6.60793734,
            2.03723764,
            0.0
        ],
        "2.367": [
            6.66462517,
            2.03980637,
            0.0
        ],
        "2.4": [
            6.71712494,
            2.04221869,
            0.0
        ],
        "2.433": [
            6.76506186,
            2.04444385,
            0.0
        ],
        "2.467": [
            6.80893707,
            2.04648137,
            0.0
        ],
        "2.5": [
            6.84974957,
            2.04836202,
            0.0
        ],
        "2.533": [
            6.88774967,
            2.05009341,
            0.0
        ],
        "2.567": [
            6.92318773,
            2.05169272,
            -4.8e-07
        ],
        "2.6": [
            6.95625019,
            2.05318141,
            0.0
        ],
        "2.633": [
            6.98731232,
            2.05456233,
            0.0
        ],
        "2.667": [
            7.01649952,
            2.05586886,
            0.0
        ],
        "2.7": [
            7.04406261,
            2.0571053,
            -4.8e-07
        ],
        "2.733": [
            7.07024956,
            2.05829358,
            0.0
        ],
        "2.767": [
            7.09537411,
            2.05944324,
            0.0
        ],
        "2.8": [
            7.11956215,
            2.06056952,
            4.8e-07
        ],
        "2.833": [
            7.14318752,
            2.06169963,
            0.0
        ],
        "2.867": [
            7.16631222,
            2.0628376,
            -4.8e-07
        ],
        "2.9": [
            7.18937492,
            2.06400013,
            0.0
        ],
        "2.933": [
            7.21249962,
            2.06521273,
            0.0
        ],
        "2.967": [
            7.23593712,
            2.06648111,
            0.0
        ],
        "3.0": [
            7.25993729,
            2.06782532,
            0.0
        ],
        "3.033": [
            7.28474951,
            2.06926274,
            4.8e-07
        ],
        "3.067": [
            7.31062508,
            2.07080626,
            0.0
        ],
        "3.1": [
            7.33774996,
            2.07247472,
            4.8e-07
        ],
        "3.133": [
            7.36643648,
            2.07428169,
            4.8e-07
        ],
        "3.167": [
            7.39693689,
            2.07624364,
            4.8e-07
        ],
        "3.2": [
            7.42943764,
            2.07837486,
            0.0
        ],
        "3.233": [
            7.46412563,
            2.08068705,
            -4.8e-07
        ],
        "3.267": [
            7.50137424,
            2.08321333,
            4.8e-07
        ],
        "3.3": [
            7.54137516,
            2.0859499,
            0.0
        ],
        "3.333": [
            7.58431244,
            2.08891916,
            0.0
        ],
        "3.367": [
            7.63049936,
            2.09214377,
            0.0
        ],
        "3.4": [
            7.68012476,
            2.09563136,
            0.0
        ],
        "3.433": [
            7.73349953,
            2.09939981,
            0.0
        ],
        "3.467": [
            7.79931259,
            2.10421848,
            4.8e-07
        ],
        "3.5": [
            7.8841877,
            2.11065602,
            -4.8e-07
        ],
        "3.533": [
            7.98493767,
            2.11845613,
            4.8e-07
        ],
        "3.567": [
            8.09837532,
            2.12734962,
            0.0
        ],
        "3.6": [
            8.22143745,
            2.13708806,
            0.0
        ],
        "3.633": [
            8.35093689,
            2.14739966,
            0.0
        ],
        "3.667": [
            8.4836874,
            2.15802407,
            -4.8e-07
        ],
        "3.7": [
            8.61662388,
            2.16870022,
            0.0
        ],
        "3.733": [
            8.74656296,
            2.1791687,
            0.0
        ],
        "3.767": [
            8.87031269,
            2.18916225,
            4.8e-07
        ],
        "3.8": [
            8.98481274,
            2.19842553,
            0.0
        ],
        "3.833": [
            9.08687496,
            2.20669365,
            0.0
        ],
        "3.867": [
            9.17337513,
            2.21370506,
            -4.8e-07
        ],
        "3.9": [
            9.24112415,
            2.21920085,
            0.0
        ],
        "3.933": [
            9.28699875,
            2.22290564,
            0.0
        ],
        "3.967": [
            9.30787468,
            2.22457457,
            -4.8e-07
        ],
        "4.0": [
            9.31506252,
            2.22513032,
            0.0
        ],
        "4.033": [
            9.32212543,
            2.22566891,
            4.8e-07
        ],
        "4.067": [
            9.32893658,
            2.22618866,
            0.0
        ],
        "4.1": [
            9.33562469,
            2.22669911,
            -4.8e-07
        ],
        "4.133": [
            9.34206295,
            2.22719359,
            0.0
        ],
        "4.167": [
            9.34837532,
            2.22767472,
            -4.8e-07
        ],
        "4.2": [
            9.35449982,
            2.22814417,
            0.0
        ],
        "4.233": [
            9.36043739,
            2.22859979,
            0.0
        ],
        "4.267": [
            9.3661871,
            2.22904325,
            -4.8e-07
        ],
        "4.3": [
            9.37181187,
            2.22946906,
            4.8e-07
        ],
        "4.333": [
            9.37724972,
            2.22988725,
            0.0
        ],
        "4.367": [
            9.38249969,
            2.2302866,
            -4.8e-07
        ],
        "4.4": [
            9.38762474,
            2.23068094,
            0.0
        ],
        "4.433": [
            9.39256287,
            2.23105574,
            -4.8e-07
        ],
        "4.467": [
            9.39731216,
            2.23142552,
            0.0
        ],
        "4.5": [
            9.40200043,
            2.23178124,
            -4.8e-07
        ],
        "4.533": [
            9.40643692,
            2.23212457,
            0.0
        ],
        "4.567": [
            9.41081238,
            2.23245668,
            0.0
        ],
        "4.6": [
            9.41499996,
            2.23277473,
            0.0
        ],
        "4.633": [
            9.41899872,
            2.23308825,
            4.8e-07
        ],
        "4.667": [
            9.42293739,
            2.23338127,
            4.8e-07
        ],
        "4.7": [
            9.42668629,
            2.23366904,
            4.8e-07
        ],
        "4.733": [
            9.4303112,
            2.23394966,
            4.8e-07
        ],
        "4.767": [
            9.43381214,
            2.2342186,
            0.0
        ],
        "4.8": [
            9.43712521,
            2.23447466,
            -4.8e-07
        ],
        "4.833": [
            9.44037533,
            2.23471904,
            4.8e-07
        ],
        "4.867": [
            9.44349861,
            2.23495555,
            0.0
        ],
        "4.9": [
            9.44643784,
            2.23518753,
            0.0
        ],
        "4.933": [
            9.44931221,
            2.23540616,
            0.0
        ],
        "4.967": [
            9.45206261,
            2.23561287,
            -4.8e-07
        ],
        "5.0": [
            9.45468712,
            2.23581219,
            4.8e-07
        ],
        "5.033": [
            9.45718765,
            2.2360065,
            4.8e-07
        ],
        "5.067": [
            9.4595623,
            2.23618722,
            4.8e-07
        ],
        "5.1": [
            9.46187496,
            2.23636317,
            4.8e-07
        ],
        "5.133": [
            9.46406269,
            2.23653078,
            0.0
        ],
        "5.167": [
            9.46612358,
            2.23669386,
            4.8e-07
        ],
        "5.2": [
            9.46812439,
            2.23684382,
            0.0
        ],
        "5.233": [
            9.47000027,
            2.23698735,
            0.0
        ],
        "5.267": [
            9.47175026,
            2.23712492,
            -4.8e-07
        ],
        "5.3": [
            9.47343636,
            2.23725009,
            -4.8e-07
        ],
        "5.333": [
            9.47506142,
            2.23737597,
            0.0
        ],
        "5.367": [
            9.4765625,
            2.23748755,
            0.0
        ],
        "5.4": [
            9.4779377,
            2.23759961,
            0.0
        ],
        "5.433": [
            9.4793129,
            2.23769999,
            -4.8e-07
        ],
        "5.467": [
            9.48056221,
            2.23779392,
            0.0
        ],
        "5.5": [
            9.48174953,
            2.23788762,
            0.0
        ],
        "5.533": [
            9.48281288,
            2.23796773,
            0.0
        ],
        "5.567": [
            9.48387527,
            2.23804998,
            -4.8e-07
        ],
        "5.6": [
            9.48481274,
            2.23812389,
            -4.8e-07
        ],
        "5.633": [
            9.48568726,
            2.2381928,
            -4.8e-07
        ],
        "5.667": [
            9.48656273,
            2.23825669,
            0.0
        ],
        "5.7": [
            9.48731232,
            2.23831296,
            -4.8e-07
        ],
        "5.733": [
            9.48799992,
            2.2383616,
            0.0
        ],
        "5.767": [
            9.48862457,
            2.23841214,
            -4.8e-07
        ],
        "5.8": [
            9.48925018,
            2.23845577,
            -4.8e-07
        ],
        "5.833": [
            9.48974991,
            2.23849964,
            -4.8e-07
        ],
        "5.867": [
            9.49024963,
            2.23853707,
            0.0
        ],
        "5.9": [
            9.49068737,
            2.23856759,
            -4.8e-07
        ],
        "5.933": [
            9.49106216,
            2.23859978,
            0.0
        ],
        "5.967": [
            9.49137402,
            2.23862529,
            4.8e-07
        ],
        "6.0": [
            9.49168682,
            2.2386508,
            4.8e-07
        ],
        "6.033": [
            9.49199963,
            2.23866868,
            0.0
        ],
        "6.067": [
            9.49218655,
            2.23868752,
            0.0
        ],
        "6.1": [
            9.49237537,
            2.23869944,
            -4.8e-07
        ],
        "6.133": [
            9.49256229,
            2.23871875,
            0.0
        ],
        "6.167": [
            9.49268627,
            2.23872447,
            0.0
        ],
        "6.2": [
            9.49281216,
            2.23873806,
            0.0
        ],
        "6.233": [
            9.49293709,
            2.23874378,
            -4.8e-07
        ],
        "6.267": [
            9.49299908,
            2.23874974,
            0.0
        ],
        "6.3": [
            9.49306297,
            2.23875022,
            0.0
        ],
        "6.333": [
            9.49306297,
            2.23875546,
            0.0
        ],
        "6.367": [
            9.49312401,
            2.23875594,
            -4.8e-07
        ],
        "6.4": [
            9.49312401,
            2.23875594,
            -4.8e-07
        ],
        "6.433": [
            9.49312401,
            2.23875594,
            -4.8e-07
        ],
        "6.467": [
            9.49312401,
            2.23875594,
            -4.8e-07
        ],
        "6.5": [
            9.49312401,
            2.23875594,
            -4.8e-07
        ],
        "6.533": [
            9.49268627,
            2.23864365,
            0.0
        ],
        "6.567": [
            9.4911871,
            2.23827386,
            0.0
        ],
        "6.6": [
            9.48837471,
            2.23761797,
            0.0
        ],
        "6.633": [
            9.48399925,
            2.23663831,
            0.0
        ],
        "6.667": [
            9.47774887,
            2.23529434,
            4.8e-07
        ],
        "6.7": [
            9.46943665,
            2.23355699,
            4.8e-07
        ],
        "6.733": [
            9.45881271,
            2.23138165,
            0.0
        ],
        "6.767": [
            9.44556236,
            2.22873735,
            0.0
        ],
        "6.8": [
            9.42943764,
            2.22559381,
            0.0
        ],
        "6.833": [
            9.41018772,
            2.22190022,
            0.0
        ],
        "6.867": [
            9.3875618,
            2.21763754,
            0.0
        ],
        "6.9": [
            9.36137486,
            2.21275568,
            0.0
        ],
        "6.933": [
            9.33125019,
            2.207232,
            0.0
        ],
        "6.967": [
            9.29693794,
            2.20101905,
            0.0
        ],
        "7.0": [
            9.25824928,
            2.19408774,
            4.8e-07
        ],
        "7.033": [
            9.21493721,
            2.18639374,
            0.0
        ],
        "7.067": [
            9.16668797,
            2.17791319,
            4.8e-07
        ],
        "7.1": [
            9.11324978,
            2.16860008,
            0.0
        ],
        "7.133": [
            9.05025005,
            2.15773749,
            0.0
        ],
        "7.167": [
            8.97443771,
            2.14481258,
            0.0
        ],
        "7.2": [
            8.88768768,
            2.13010001,
            0.0
        ],
        "7.233": [
            8.79168701,
            2.11388111,
            0.0
        ],
        "7.267": [
            8.68812466,
            2.09643745,
            0.0
        ],
        "7.3": [
            8.57874966,
            2.07803726,
            0.0
        ],
        "7.333": [
            8.46531296,
            2.05895615,
            0.0
        ],
        "7.367": [
            8.34956264,
            2.03948808,
            0.0
        ],
        "7.4": [
            8.23318672,
            2.01989365,
            0.0
        ],
        "7.433": [
            8.11793709,
            2.00045586,
            0.0
        ],
        "7.467": [
            8.00556278,
            1.9814558,
            0.0
        ],
        "7.5": [
            7.89774942,
            1.96316886,
            0.0
        ],
        "7.533": [
            7.79631233,
            1.94587469,
            -4.8e-07
        ],
        "7.567": [
            7.70293713,
            1.9298439,
            4.8e-07
        ],
        "7.6": [
            7.61931181,
            1.91536212,
            0.0
        ],
        "7.633": [
            7.54724979,
            1.90269971,
            0.0
        ],
        "7.667": [
            7.48843765,
            1.89214396,
            0.0
        ],
        "7.7": [
            7.4446249,
            1.88396239,
            0.0
        ],
        "7.733": [
            7.41749954,
            1.87843752,
            4.8e-07
        ],
        "7.767": [
            7.40037489,
            1.87455606,
            0.0
        ],
        "7.8": [
            7.38506222,
            1.87110686,
            4.8e-07
        ],
        "7.833": [
            7.37162495,
            1.86806226,
            0.0
        ],
        "7.867": [
            7.35981274,
            1.86539364,
            0.0
        ],
        "7.9": [
            7.34962463,
            1.86308694,
            0.0
        ],
        "7.933": [
            7.34081268,
            1.86110568,
            0.0
        ],
        "7.967": [
            7.33343697,
            1.85942507,
            4.8e-07
        ],
        "8.0": [
            7.32724953,
            1.85803175,
            0.0
        ],
        "8.033": [
            7.32218742,
            1.85688758,
            0.0
        ],
        "8.067": [
            7.31812477,
            1.85596848,
            0.0
        ],
        "8.1": [
            7.31493759,
            1.85525584,
            -4.8e-07
        ],
        "8.133": [
            7.31256199,
            1.85471869,
            0.0
        ],
        "8.167": [
            7.31087399,
            1.85433102,
            4.8e-07
        ],
        "8.2": [
            7.3097496,
            1.85407543,
            4.8e-07
        ],
        "8.233": [
            7.30906248,
            1.85391855,
            0.0
        ],
        "8.267": [
            7.30868769,
            1.85383749,
            0.0
        ],
        "8.3": [
            7.30856228,
            1.85381222,
            0.0
        ],
        "8.333": [
            7.30856228,
            1.8538065,
            0.0
        ]
    },
    "rotation": {
        "0.0": [
            -7.3e-07,
            89.99985504,
            7.3e-07
        ],
        "0.033": [
            -7.3e-07,
            89.99985504,
            7.3e-07
        ],
        "0.067": [
            -7.3e-07,
            89.99985504,
            7.3e-07
        ],
        "0.1": [
            -7.3e-07,
            89.99985504,
            7.3e-07
        ],
        "0.133": [
            -7.3e-07,
            89.99985504,
            7.3e-07
        ],
        "0.167": [
            -7.3e-07,
            89.99985504,
            7.3e-07
        ],
        "0.2": [
            -7.3e-07,
            89.99985504,
            7.3e-07
        ],
        "0.233": [
            -7.3e-07,
            89.99985504,
            7.3e-07
        ],
        "0.267": [
            -7.3e-07,
            89.99985504,
            7.3e-07
        ],
        "0.3": [
            -7.3e-07,
            89.99985504,
            7.3e-07
        ],
        "0.333": [
            -7.3e-07,
            89.99985504,
            7.3e-07
        ],
        "0.367": [
            -7.3e-07,
            89.99985504,
            7.3e-07
        ],
        "0.4": [
            -7.3e-07,
            89.99985504,
            7.3e-07
        ],
        "0.433": [
            -7.3e-07,
            89.99985504,
            7.3e-07
        ],
        "0.467": [
            -7.3e-07,
            89.99985504,
            7.3e-07
        ],
        "0.5": [
            -7.3e-07,
            89.99985504,
            7.3e-07
        ],
        "0.533": [
            -7.3e-07,
            89.99985504,
            7.3e-07
        ],
        "0.567": [
            -7.3e-07,
            89.99985504,
            7.3e-07
        ],
        "0.6": [
            -7.3e-07,
            89.99985504,
            7.3e-07
        ],
        "0.633": [
            -7.3e-07,
            89.99985504,
            7.3e-07
        ],
        "0.667": [
            -7.3e-07,
            89.99985504,
            7.3e-07
        ],
        "0.7": [
            -7.3e-07,
            89.99985504,
            7.3e-07
        ],
        "0.733": [
            -7.3e-07,
            89.99985504,
            7.3e-07
        ],
        "0.767": [
            -7.3e-07,
            89.99985504,
            7.3e-07
        ],
        "0.8": [
            -7.3e-07,
            89.99985504,
            7.3e-07
        ],
        "0.833": [
            -7.3e-07,
            89.99985504,
            7.3e-07
        ],
        "0.867": [
            -7.3e-07,
            89.99985504,
            7.3e-07
        ],
        "0.9": [
            -7.3e-07,
            89.99985504,
            7.3e-07
        ],
        "0.933": [
            -7.3e-07,
            89.99985504,
            7.3e-07
        ],
        "0.967": [
            -7.3e-07,
            89.99985504,
            7.3e-07
        ],
        "1.0": [
            -7.3e-07,
            89.99985504,
            7.3e-07
        ],
        "1.033": [
            -7.3e-07,
            89.99985504,
            7.3e-07
        ],
        "1.067": [
            -7.3e-07,
            89.99985504,
            7.3e-07
        ],
        "1.1": [
            -7.3e-07,
            89.99985504,
            7.3e-07
        ],
        "1.133": [
            -7.3e-07,
            89.99985504,
            7.3e-07
        ],
        "1.167": [
            -7.3e-07,
            89.99985504,
            7.3e-07
        ],
        "1.2": [
            -7.3e-07,
            89.99985504,
            7.3e-07
        ],
        "1.233": [
            -7.3e-07,
            89.99985504,
            7.3e-07
        ],
        "1.267": [
            -7.3e-07,
            89.99985504,
            7.3e-07
        ],
        "1.3": [
            -7.3e-07,
            89.99985504,
            7.3e-07
        ],
        "1.333": [
            -7.3e-07,
            89.99985504,
            7.3e-07
        ],
        "1.367": [
            -7.3e-07,
            89.99985504,
            7.3e-07
        ],
        "1.4": [
            -7.3e-07,
            89.99985504,
            7.3e-07
        ],
        "1.433": [
            -7.3e-07,
            89.99985504,
            7.3e-07
        ],
        "1.467": [
            -7.3e-07,
            89.99985504,
            7.3e-07
        ],
        "1.5": [
            -7.3e-07,
            89.99985504,
            7.3e-07
        ],
        "1.533": [
            -7.3e-07,
            89.99985504,
            7.3e-07
        ],
        "1.567": [
            -7.3e-07,
            89.99985504,
            7.3e-07
        ],
        "1.6": [
            -7.3e-07,
            89.99985504,
            7.3e-07
        ],
        "1.633": [
            -7.3e-07,
            89.99985504,
            7.3e-07
        ],
        "1.667": [
            -7.3e-07,
            89.99985504,
            7.3e-07
        ],
        "1.7": [
            -7.3e-07,
            89.99985504,
            7.3e-07
        ],
        "1.733": [
            -7.3e-07,
            89.99985504,
            7.3e-07
        ],
        "1.767": [
            -7.3e-07,
            89.99985504,
            7.3e-07
        ],
        "1.8": [
            -7.3e-07,
            89.99985504,
            7.3e-07
        ],
        "1.833": [
            8.78e-06,
            90.00003052,
            8.8e-07
        ],
        "1.867": [
            8.78e-06,
            90.00003052,
            8.8e-07
        ],
        "1.9": [
            8.78e-06,
            90.00003052,
            8.8e-07
        ],
        "1.933": [
            8.78e-06,
            90.00003052,
            8.8e-07
        ],
        "1.967": [
            8.78e-06,
            90.00003052,
            8.8e-07
        ],
        "2.0": [
            8.78e-06,
            90.00003052,
            8.8e-07
        ],
        "2.033": [
            8.78e-06,
            90.00003052,
            8.8e-07
        ],
        "2.067": [
            8.78e-06,
            90.00003052,
            8.8e-07
        ],
        "2.1": [
            8.78e-06,
            90.00003052,
            8.8e-07
        ],
        "2.133": [
            8.78e-06,
            90.00003052,
            8.8e-07
        ],
        "2.167": [
            8.78e-06,
            90.00003052,
            8.8e-07
        ],
        "2.2": [
            8.78e-06,
            90.00003052,
            8.8e-07
        ],
        "2.233": [
            8.78e-06,
            90.00003052,
            8.8e-07
        ],
        "2.267": [
            8.78e-06,
            90.00003052,
            8.8e-07
        ],
        "2.3": [
            8.78e-06,
            90.00003052,
            8.8e-07
        ],
        "2.333": [
            8.78e-06,
            90.00003052,
            8.8e-07
        ],
        "2.367": [
            8.78e-06,
            90.00003052,
            8.8e-07
        ],
        "2.4": [
            8.78e-06,
            90.00003052,
            8.8e-07
        ],
        "2.433": [
            8.78e-06,
            90.00003052,
            8.8e-07
        ],
        "2.467": [
            8.78e-06,
            90.00003052,
            8.8e-07
        ],
        "2.5": [
            8.78e-06,
            90.00003052,
            8.8e-07
        ],
        "2.533": [
            8.78e-06,
            90.00003052,
            8.8e-07
        ],
        "2.567": [
            8.78e-06,
            90.00003052,
            8.8e-07
        ],
        "2.6": [
            8.78e-06,
            90.00003052,
            8.8e-07
        ],
        "2.633": [
            8.78e-06,
            90.00003052,
            8.8e-07
        ],
        "2.667": [
            8.78e-06,
            90.00003052,
            8.8e-07
        ],
        "2.7": [
            8.78e-06,
            90.00003052,
            8.8e-07
        ],
        "2.733": [
            8.78e-06,
            90.00003052,
            8.8e-07
        ],
        "2.767": [
            8.78e-06,
            90.00003052,
            8.8e-07
        ],
        "2.8": [
            8.78e-06,
            90.00003052,
            8.8e-07
        ],
        "2.833": [
            8.78e-06,
            90.00003052,
            8.8e-07
        ],
        "2.867": [
            8.78e-06,
            90.00003052,
            8.8e-07
        ],
        "2.9": [
            8.78e-06,
            90.00003052,
            8.8e-07
        ],
        "2.933": [
            8.78e-06,
            90.00003052,
            8.8e-07
        ],
        "2.967": [
            8.78e-06,
            90.00003052,
            8.8e-07
        ],
        "3.0": [
            8.78e-06,
            90.00003052,
            8.8e-07
        ],
        "3.033": [
            8.78e-06,
            90.00003052,
            8.8e-07
        ],
        "3.067": [
            -7.3e-07,
            89.99985504,
            7.3e-07
        ],
        "3.1": [
            -7.3e-07,
            89.99985504,
            7.3e-07
        ],
        "3.133": [
            -7.3e-07,
            89.99985504,
            7.3e-07
        ],
        "3.167": [
            -7.3e-07,
            89.99985504,
            7.3e-07
        ],
        "3.2": [
            -7.3e-07,
            89.99985504,
            7.3e-07
        ],
        "3.233": [
            -7.3e-07,
            89.99985504,
            7.3e-07
        ],
        "3.267": [
            -7.3e-07,
            89.99985504,
            7.3e-07
        ],
        "3.3": [
            -7.3e-07,
            89.99985504,
            7.3e-07
        ],
        "3.333": [
            -7.3e-07,
            89.99985504,
            7.3e-07
        ],
        "3.367": [
            -7.3e-07,
            89.99985504,
            7.3e-07
        ],
        "3.4": [
            -7.3e-07,
            89.99985504,
            7.3e-07
        ],
        "3.433": [
            -7.3e-07,
            89.99985504,
            7.3e-07
        ],
        "3.467": [
            -7.3e-07,
            89.99985504,
            7.3e-07
        ],
        "3.5": [
            -7.3e-07,
            89.99985504,
            7.3e-07
        ],
        "3.533": [
            -7.3e-07,
            89.99985504,
            7.3e-07
        ],
        "3.567": [
            -7.3e-07,
            89.99985504,
            7.3e-07
        ],
        "3.6": [
            -7.3e-07,
            89.99985504,
            7.3e-07
        ],
        "3.633": [
            -7.3e-07,
            89.99985504,
            7.3e-07
        ],
        "3.667": [
            -7.3e-07,
            89.99985504,
            7.3e-07
        ],
        "3.7": [
            -7.3e-07,
            89.99985504,
            7.3e-07
        ],
        "3.733": [
            -7.3e-07,
            89.99985504,
            7.3e-07
        ],
        "3.767": [
            -7.3e-07,
            89.99985504,
            7.3e-07
        ],
        "3.8": [
            -7.3e-07,
            89.99985504,
            7.3e-07
        ],
        "3.833": [
            -7.3e-07,
            89.99985504,
            7.3e-07
        ],
        "3.867": [
            -7.3e-07,
            89.99985504,
            7.3e-07
        ],
        "3.9": [
            -7.3e-07,
            89.99985504,
            7.3e-07
        ],
        "3.933": [
            -7.3e-07,
            89.99985504,
            7.3e-07
        ],
        "3.967": [
            -7.3e-07,
            89.99985504,
            7.3e-07
        ],
        "4.0": [
            -7.3e-07,
            89.99985504,
            7.3e-07
        ],
        "4.033": [
            -7.3e-07,
            89.99985504,
            7.3e-07
        ],
        "4.067": [
            -7.3e-07,
            89.99985504,
            7.3e-07
        ],
        "4.1": [
            -7.3e-07,
            89.99985504,
            7.3e-07
        ],
        "4.133": [
            -7.3e-07,
            89.99985504,
            7.3e-07
        ],
        "4.167": [
            -7.3e-07,
            89.99985504,
            7.3e-07
        ],
        "4.2": [
            -7.3e-07,
            89.99985504,
            7.3e-07
        ],
        "4.233": [
            -7.3e-07,
            89.99985504,
            7.3e-07
        ],
        "4.267": [
            -7.3e-07,
            89.99985504,
            7.3e-07
        ],
        "4.3": [
            -7.3e-07,
            89.99985504,
            7.3e-07
        ],
        "4.333": [
            -7.3e-07,
            89.99985504,
            7.3e-07
        ],
        "4.367": [
            -7.3e-07,
            89.99985504,
            7.3e-07
        ],
        "4.4": [
            -7.3e-07,
            89.99985504,
            7.3e-07
        ],
        "4.433": [
            -7.3e-07,
            89.99985504,
            7.3e-07
        ],
        "4.467": [
            -7.3e-07,
            89.99985504,
            7.3e-07
        ],
        "4.5": [
            -7.3e-07,
            89.99985504,
            7.3e-07
        ],
        "4.533": [
            -7.3e-07,
            89.99985504,
            7.3e-07
        ],
        "4.567": [
            -7.3e-07,
            89.99985504,
            7.3e-07
        ],
        "4.6": [
            -7.3e-07,
            89.99985504,
            7.3e-07
        ],
        "4.633": [
            -7.3e-07,
            89.99985504,
            7.3e-07
        ],
        "4.667": [
            -7.3e-07,
            89.99985504,
            7.3e-07
        ],
        "4.7": [
            -7.3e-07,
            89.99985504,
            7.3e-07
        ],
        "4.733": [
            -7.3e-07,
            89.99985504,
            7.3e-07
        ],
        "4.767": [
            -7.3e-07,
            89.99985504,
            7.3e-07
        ],
        "4.8": [
            -7.3e-07,
            89.99985504,
            7.3e-07
        ],
        "4.833": [
            -7.3e-07,
            89.99985504,
            7.3e-07
        ],
        "4.867": [
            -7.3e-07,
            89.99985504,
            7.3e-07
        ],
        "4.9": [
            -7.3e-07,
            89.99985504,
            7.3e-07
        ],
        "4.933": [
            -7.3e-07,
            89.99985504,
            7.3e-07
        ],
        "4.967": [
            -7.3e-07,
            89.99985504,
            7.3e-07
        ],
        "5.0": [
            -7.3e-07,
            89.99985504,
            7.3e-07
        ],
        "5.033": [
            -7.3e-07,
            89.99985504,
            7.3e-07
        ],
        "5.067": [
            -7.3e-07,
            89.99985504,
            7.3e-07
        ],
        "5.1": [
            -7.3e-07,
            89.99985504,
            7.3e-07
        ],
        "5.133": [
            -7.3e-07,
            89.99985504,
            7.3e-07
        ],
        "5.167": [
            -7.3e-07,
            89.99985504,
            7.3e-07
        ],
        "5.2": [
            -7.3e-07,
            89.99985504,
            7.3e-07
        ],
        "5.233": [
            -7.3e-07,
            89.99985504,
            7.3e-07
        ],
        "5.267": [
            -7.3e-07,
            89.99985504,
            7.3e-07
        ],
        "5.3": [
            -7.3e-07,
            89.99985504,
            7.3e-07
        ],
        "5.333": [
            -7.3e-07,
            89.99985504,
            7.3e-07
        ],
        "5.367": [
            -7.3e-07,
            89.99985504,
            7.3e-07
        ],
        "5.4": [
            -7.3e-07,
            89.99985504,
            7.3e-07
        ],
        "5.433": [
            -7.3e-07,
            89.99985504,
            7.3e-07
        ],
        "5.467": [
            -7.3e-07,
            89.99985504,
            7.3e-07
        ],
        "5.5": [
            -7.3e-07,
            89.99985504,
            7.3e-07
        ],
        "5.533": [
            -7.3e-07,
            89.99985504,
            7.3e-07
        ],
        "5.567": [
            -7.3e-07,
            89.99985504,
            7.3e-07
        ],
        "5.6": [
            -7.3e-07,
            89.99985504,
            7.3e-07
        ],
        "5.633": [
            -7.3e-07,
            89.99985504,
            7.3e-07
        ],
        "5.667": [
            -7.3e-07,
            89.99985504,
            7.3e-07
        ],
        "5.7": [
            -7.3e-07,
            89.99985504,
            7.3e-07
        ],
        "5.733": [
            -7.3e-07,
            89.99985504,
            7.3e-07
        ],
        "5.767": [
            -7.3e-07,
            89.99985504,
            7.3e-07
        ],
        "5.8": [
            -7.3e-07,
            89.99985504,
            7.3e-07
        ],
        "5.833": [
            -7.3e-07,
            89.99985504,
            7.3e-07
        ],
        "5.867": [
            -7.3e-07,
            89.99985504,
            7.3e-07
        ],
        "5.9": [
            -7.3e-07,
            89.99985504,
            7.3e-07
        ],
        "5.933": [
            -7.3e-07,
            89.99985504,
            7.3e-07
        ],
        "5.967": [
            -7.3e-07,
            89.99985504,
            7.3e-07
        ],
        "6.0": [
            -7.3e-07,
            89.99985504,
            7.3e-07
        ],
        "6.033": [
            -7.3e-07,
            89.99985504,
            7.3e-07
        ],
        "6.067": [
            -7.3e-07,
            89.99985504,
            7.3e-07
        ],
        "6.1": [
            -7.3e-07,
            89.99985504,
            7.3e-07
        ],
        "6.133": [
            -7.3e-07,
            89.99985504,
            7.3e-07
        ],
        "6.167": [
            -7.3e-07,
            89.99985504,
            7.3e-07
        ],
        "6.2": [
            -7.3e-07,
            89.99985504,
            7.3e-07
        ],
        "6.233": [
            -7.3e-07,
            89.99985504,
            7.3e-07
        ],
        "6.267": [
            -7.3e-07,
            89.99985504,
            7.3e-07
        ],
        "6.3": [
            -7.3e-07,
            89.99985504,
            7.3e-07
        ],
        "6.333": [
            -7.3e-07,
            89.99985504,
            7.3e-07
        ],
        "6.367": [
            -7.3e-07,
            89.99985504,
            7.3e-07
        ],
        "6.4": [
            -7.3e-07,
            89.99985504,
            7.3e-07
        ],
        "6.433": [
            -7.3e-07,
            89.99985504,
            7.3e-07
        ],
        "6.467": [
            -7.3e-07,
            89.99985504,
            7.3e-07
        ],
        "6.5": [
            -7.3e-07,
            89.99985504,
            7.3e-07
        ],
        "6.533": [
            -7.3e-07,
            89.99985504,
            7.3e-07
        ],
        "6.567": [
            -7.3e-07,
            89.99985504,
            7.3e-07
        ],
        "6.6": [
            -7.3e-07,
            89.99985504,
            7.3e-07
        ],
        "6.633": [
            -7.3e-07,
            89.99985504,
            7.3e-07
        ],
        "6.667": [
            -7.3e-07,
            89.99985504,
            7.3e-07
        ],
        "6.7": [
            -7.3e-07,
            89.99985504,
            7.3e-07
        ],
        "6.733": [
            -7.3e-07,
            89.99985504,
            7.3e-07
        ],
        "6.767": [
            -7.3e-07,
            89.99985504,
            7.3e-07
        ],
        "6.8": [
            -7.3e-07,
            89.99985504,
            7.3e-07
        ],
        "6.833": [
            -7.3e-07,
            89.99985504,
            7.3e-07
        ],
        "6.867": [
            -7.3e-07,
            89.99985504,
            7.3e-07
        ],
        "6.9": [
            -7.3e-07,
            89.99985504,
            7.3e-07
        ],
        "6.933": [
            -7.3e-07,
            89.99985504,
            7.3e-07
        ],
        "6.967": [
            -7.3e-07,
            89.99985504,
            7.3e-07
        ],
        "7.0": [
            -7.3e-07,
            89.99985504,
            7.3e-07
        ],
        "7.033": [
            -7.3e-07,
            89.99985504,
            7.3e-07
        ],
        "7.067": [
            -7.3e-07,
            89.99985504,
            7.3e-07
        ],
        "7.1": [
            -7.3e-07,
            89.99985504,
            7.3e-07
        ],
        "7.133": [
            -7.3e-07,
            89.99985504,
            7.3e-07
        ],
        "7.167": [
            -7.3e-07,
            89.99985504,
            7.3e-07
        ],
        "7.2": [
            -7.3e-07,
            89.99985504,
            7.3e-07
        ],
        "7.233": [
            -7.3e-07,
            89.99985504,
            7.3e-07
        ],
        "7.267": [
            -7.3e-07,
            89.99985504,
            7.3e-07
        ],
        "7.3": [
            -7.3e-07,
            89.99985504,
            7.3e-07
        ],
        "7.333": [
            -7.3e-07,
            89.99985504,
            7.3e-07
        ],
        "7.367": [
            -7.3e-07,
            89.99985504,
            7.3e-07
        ],
        "7.4": [
            -7.3e-07,
            89.99985504,
            7.3e-07
        ],
        "7.433": [
            -7.3e-07,
            89.99985504,
            7.3e-07
        ],
        "7.467": [
            -7.3e-07,
            89.99985504,
            7.3e-07
        ],
        "7.5": [
            -7.3e-07,
            89.99985504,
            7.3e-07
        ],
        "7.533": [
            -7.3e-07,
            89.99985504,
            7.3e-07
        ],
        "7.567": [
            -7.3e-07,
            89.99985504,
            7.3e-07
        ],
        "7.6": [
            -7.3e-07,
            89.99985504,
            7.3e-07
        ],
        "7.633": [
            -7.3e-07,
            89.99985504,
            7.3e-07
        ],
        "7.667": [
            -7.3e-07,
            89.99985504,
            7.3e-07
        ],
        "7.7": [
            -7.3e-07,
            89.99985504,
            7.3e-07
        ],
        "7.733": [
            -7.3e-07,
            89.99985504,
            7.3e-07
        ],
        "7.767": [
            -7.3e-07,
            89.99985504,
            7.3e-07
        ],
        "7.8": [
            -7.3e-07,
            89.99985504,
            7.3e-07
        ],
        "7.833": [
            -7.3e-07,
            89.99985504,
            7.3e-07
        ],
        "7.867": [
            -7.3e-07,
            89.99985504,
            7.3e-07
        ],
        "7.9": [
            -7.3e-07,
            89.99985504,
            7.3e-07
        ],
        "7.933": [
            -7.3e-07,
            89.99985504,
            7.3e-07
        ],
        "7.967": [
            -7.3e-07,
            89.99985504,
            7.3e-07
        ],
        "8.0": [
            -7.3e-07,
            89.99985504,
            7.3e-07
        ],
        "8.033": [
            -7.3e-07,
            89.99985504,
            7.3e-07
        ],
        "8.067": [
            -7.3e-07,
            89.99985504,
            7.3e-07
        ],
        "8.1": [
            -7.3e-07,
            89.99985504,
            7.3e-07
        ],
        "8.133": [
            -7.3e-07,
            89.99985504,
            7.3e-07
        ],
        "8.167": [
            -7.3e-07,
            89.99985504,
            7.3e-07
        ],
        "8.2": [
            -7.3e-07,
            89.99985504,
            7.3e-07
        ],
        "8.233": [
            -7.3e-07,
            89.99985504,
            7.3e-07
        ],
        "8.267": [
            -7.3e-07,
            89.99985504,
            7.3e-07
        ],
        "8.3": [
            -7.3e-07,
            89.99985504,
            7.3e-07
        ],
        "8.333": [
            -7.3e-07,
            89.99985504,
            7.3e-07
        ]
    }
}